alibabacloud_aliding20230426/__init__.py
alibabacloud_aliding20230426/client.py
alibabacloud_aliding20230426/models/__init__.py
alibabacloud_aliding20230426/models/_add_attendee_headers.py
alibabacloud_aliding20230426/models/_add_attendee_request.py
alibabacloud_aliding20230426/models/_add_attendee_response.py
alibabacloud_aliding20230426/models/_add_attendee_response_body.py
alibabacloud_aliding20230426/models/_add_attendee_shrink_headers.py
alibabacloud_aliding20230426/models/_add_attendee_shrink_request.py
alibabacloud_aliding20230426/models/_add_drive_space_headers.py
alibabacloud_aliding20230426/models/_add_drive_space_request.py
alibabacloud_aliding20230426/models/_add_drive_space_response.py
alibabacloud_aliding20230426/models/_add_drive_space_response_body.py
alibabacloud_aliding20230426/models/_add_drive_space_shrink_headers.py
alibabacloud_aliding20230426/models/_add_drive_space_shrink_request.py
alibabacloud_aliding20230426/models/_add_folder_headers.py
alibabacloud_aliding20230426/models/_add_folder_request.py
alibabacloud_aliding20230426/models/_add_folder_response.py
alibabacloud_aliding20230426/models/_add_folder_response_body.py
alibabacloud_aliding20230426/models/_add_folder_shrink_headers.py
alibabacloud_aliding20230426/models/_add_folder_shrink_request.py
alibabacloud_aliding20230426/models/_add_meeting_rooms_headers.py
alibabacloud_aliding20230426/models/_add_meeting_rooms_request.py
alibabacloud_aliding20230426/models/_add_meeting_rooms_response.py
alibabacloud_aliding20230426/models/_add_meeting_rooms_response_body.py
alibabacloud_aliding20230426/models/_add_meeting_rooms_shrink_headers.py
alibabacloud_aliding20230426/models/_add_meeting_rooms_shrink_request.py
alibabacloud_aliding20230426/models/_add_multi_dim_table_headers.py
alibabacloud_aliding20230426/models/_add_multi_dim_table_request.py
alibabacloud_aliding20230426/models/_add_multi_dim_table_response.py
alibabacloud_aliding20230426/models/_add_multi_dim_table_response_body.py
alibabacloud_aliding20230426-2.47.2.dist-info/LICENSE
alibabacloud_aliding20230426-2.47.2.dist-info/METADATA
alibabacloud_aliding20230426-2.47.2.dist-info/WHEEL
alibabacloud_aliding20230426-2.47.2.dist-info/top_level.txt
alibabacloud_aliding20230426-2.47.2.dist-info/RECORD
